setup.py
sklab2.egg-info/PKG-INFO
sklab2.egg-info/SOURCES.txt
sklab2.egg-info/dependency_links.txt
sklab2.egg-info/requires.txt
sklab2.egg-info/top_level.txt
sksksksk/__init__.py
sksksksk/cFunction.py